simple_cache/__init__.py
simple_cache/cache_data.py
simple_cache/providers/__init__.py
simple_cache/providers/deta.py
simple_cache/providers/file.py
simple_cache/providers/provider.py
mgdl_simple_cache-1.2.1.dist-info/LICENSE
mgdl_simple_cache-1.2.1.dist-info/METADATA
mgdl_simple_cache-1.2.1.dist-info/WHEEL
mgdl_simple_cache-1.2.1.dist-info/top_level.txt
mgdl_simple_cache-1.2.1.dist-info/RECORD
