Metadata-Version: 2.1
Name: mgdl-simple-cache
Version: 1.2.1
Summary: Simple Cache is a lightweight cache manager designed to simplify caching operations using providers. It offers a convenient way to store and retrieve cached data efficiently in Python applications.
Author-email: Adaías Magdiel <eu@adaiasmagdiel.com>
License: Copyright (c) 2024 Adaías Magdiel
Project-URL: Homepage, https://github.com/AdaiasMagdiel/simple-cache
Project-URL: Issues, https://github.com/AdaiasMagdiel/simple-cache/issues
Keywords: cache,caching,deta,deta space,development,utility,tool
Classifier: License :: OSI Approved :: MIT License
Classifier: Intended Audience :: Developers
Classifier: Topic :: Software Development :: Libraries :: Python Modules
Classifier: Operating System :: OS Independent
Classifier: Programming Language :: Python :: 3
Classifier: Programming Language :: Python :: 3 :: Only
Classifier: Natural Language :: English
Classifier: License :: OSI Approved :: MIT License
Classifier: Topic :: Software Development :: Libraries
Classifier: Topic :: Utilities
Requires-Python: >=3.6
License-File: LICENSE
Requires-Dist: deta
Provides-Extra: dev
Requires-Dist: pytest ; extra == 'dev'
Requires-Dist: pytest-cov ; extra == 'dev'
